coating/__init__.py
coating/__main__.py
coating/parser.py
coating/view.py
coating-0.0.2.dist-info/LICENSE
coating-0.0.2.dist-info/METADATA
coating-0.0.2.dist-info/WHEEL
coating-0.0.2.dist-info/entry_points.txt
coating-0.0.2.dist-info/top_level.txt
coating-0.0.2.dist-info/RECORD
