Metadata-Version: 2.1
Name: coating
Version: 0.0.2
Summary: A filter with an pointer interface 🦝
Author-email: Pieli <pieli.dev@gmail.com>
Project-URL: Homepage, https://github.com/Pieli/coating
Project-URL: Bug Tracker, https://github.com/Pieli/coating/issues
Keywords: vim,bash,cli,unix,rice,tui,hci,interaction,unix-philosophy
Classifier: Programming Language :: Python :: 3
Classifier: License :: OSI Approved :: GNU General Public License v3 (GPLv3)
Classifier: Operating System :: OS Independent
Classifier: Environment :: Console
Classifier: Intended Audience :: Developers
Classifier: Intended Audience :: Science/Research
Classifier: Intended Audience :: System Administrators
Classifier: Topic :: Utilities
Classifier: Topic :: Software Development :: Libraries
Classifier: Topic :: Scientific/Engineering :: Visualization
Requires-Python: >=3.8
License-File: LICENSE
Requires-Dist: beautifulsoup4 ==4.12.2
Requires-Dist: bs4 ==0.0.1
Requires-Dist: lxml ==4.9.3
Requires-Dist: soupsieve ==2.5
